osprey_design/__init__.py
osprey_design/cli.py
osprey_design/globals.py
osprey_design/navigation.py
osprey_design/osprey_design.py
osprey_design-0.1.1.dist-info/AUTHORS.rst
osprey_design-0.1.1.dist-info/LICENSE
osprey_design-0.1.1.dist-info/METADATA
osprey_design-0.1.1.dist-info/WHEEL
osprey_design-0.1.1.dist-info/entry_points.txt
osprey_design-0.1.1.dist-info/top_level.txt
osprey_design-0.1.1.dist-info/RECORD
