Metadata-Version: 2.1
Name: osprey-design
Version: 0.1.1
Summary: Provides a workflow to help you create reproducable OSPREY designs
Home-page: https://github.com/gusennan/osprey_design
Author: Nate Guerin
Author-email: nate@textpla.in
License: GNU General Public License v3
Keywords: osprey_design
Platform: UNKNOWN
Classifier: Development Status :: 2 - Pre-Alpha
Classifier: Intended Audience :: Developers
Classifier: License :: OSI Approved :: GNU General Public License v3 (GPLv3)
Classifier: Natural Language :: English
Classifier: Programming Language :: Python :: 2
Classifier: Programming Language :: Python :: 2.7
Classifier: Programming Language :: Python :: 3
Classifier: Programming Language :: Python :: 3.4
Classifier: Programming Language :: Python :: 3.5
Classifier: Programming Language :: Python :: 3.6
Requires-Dist: Click (>=6.0)
